markdownserver/__init__.py
markdownserver/env.py
markdownserver/markdown_converter.py
markdownserver/resources/css/github.css
markdownserver/resources/html/sample.md.html
markdownserver/resources/markdown/sample.md
markdown_server-0.1.4.dist-info/LICENSE.txt
markdown_server-0.1.4.dist-info/METADATA
markdown_server-0.1.4.dist-info/WHEEL
markdown_server-0.1.4.dist-info/entry_points.txt
markdown_server-0.1.4.dist-info/top_level.txt
markdown_server-0.1.4.dist-info/RECORD
