Metadata-Version: 1.1
Name: markdown-server
Version: 0.1.4
Summary: A simple markdown server.
Home-page: https://github.com/ohbarye/markdown-server
Author: Masato Ohba
Author-email: over.rye@gmail.com
License: MIT License
Keywords: web,markdown
Platform: UNKNOWN
Classifier: Topic :: Utilities
Classifier: Development Status :: 4 - Beta
Classifier: Framework :: Bottle
Classifier: License :: OSI Approved :: MIT License
Classifier: Programming Language :: Python
Classifier: Programming Language :: Python :: 2.7
Classifier: Programming Language :: Python :: 3
